quickbolt/__init__.py
quickbolt/batch_generation/__init__.py
quickbolt/batch_generation/batch_generation.py
quickbolt/clients/__init__.py
quickbolt/clients/aio_grpc.py
quickbolt/clients/aio_requests.py
quickbolt/clients/httpx_requests.py
quickbolt/logging/__init__.py
quickbolt/logging/async_logger.py
quickbolt/pytest/__init__.py
quickbolt/pytest/core_pytest_base.py
quickbolt/reporting/__init__.py
quickbolt/reporting/response_csv.py
quickbolt/utils/__init__.py
quickbolt/utils/dictionary.py
quickbolt/utils/directory.py
quickbolt/utils/json.py
quickbolt/utils/sync_async.py
quickbolt/validations/__init__.py
quickbolt/validations/validations.py
quickbolt-0.4.3.dist-info/METADATA
quickbolt-0.4.3.dist-info/WHEEL
quickbolt-0.4.3.dist-info/licenses/LICENSE
quickbolt-0.4.3.dist-info/RECORD
