Metadata-Version: 2.4
Name: quickbolt
Version: 0.4.3
Summary: Asynchronously make and validate requests!
License: MIT
License-File: LICENSE
Author: Ashton Szabo
Author-email: aszabo00@gmail.com
Requires-Python: >=3.11,<4.0
Classifier: Intended Audience :: Developers
Classifier: Intended Audience :: Information Technology
Classifier: License :: OSI Approved :: MIT License
Classifier: Operating System :: OS Independent
Classifier: Programming Language :: Python :: 3
Classifier: Programming Language :: Python :: 3.11
Classifier: Programming Language :: Python :: 3.12
Classifier: Programming Language :: Python :: 3.13
Classifier: Programming Language :: Python :: 3.14
Classifier: Topic :: Software Development :: Libraries
Classifier: Topic :: Software Development :: Testing
Classifier: Typing :: Typed
Requires-Dist: aiocsv (>=1.4.0,<2.0.0)
Requires-Dist: aiofiles (>=25.1.0,<26.0.0)
Requires-Dist: aiohttp[speedups] (>=3.13.0,<4.0.0)
Requires-Dist: aiologger (>=0.7.0,<0.8.0)
Requires-Dist: grpcio (>=1.75.1,<2.0.0)
Requires-Dist: grpcio-tools (>=1.75.1,<2.0.0)
Requires-Dist: httpx[http2] (>=0.28.1,<0.29.0)
Requires-Dist: numpy (>=2.3.4,<3.0.0)
Requires-Dist: orjson (>=3.11.3,<4.0.0)
Requires-Dist: pypeln (>=0.4.9,<0.5.0)
Requires-Dist: pytest (>=8.4.2,<9.0.0)
Requires-Dist: pytest-asyncio (>=1.2.0,<2.0.0)
Requires-Dist: pytest-xdist (>=3.8.0,<4.0.0)
Requires-Dist: uvloop (>=0.21.0,<0.22.0)
Project-URL: Repository, https://github.com/aszabo00/quickbolt
